ggee/__init__.py
ggee/ggee.py
ggee-0.0.1.dist-info/LICENSE.txt
ggee-0.0.1.dist-info/METADATA
ggee-0.0.1.dist-info/WHEEL
ggee-0.0.1.dist-info/top_level.txt
ggee-0.0.1.dist-info/RECORD
