Metadata-Version: 2.1
Name: ggee
Version: 0.0.1
Summary: A Python package for Google Earth Engine Tools
Home-page: https://github.com/tnmthai/ggee
Author: Thai Tran
Author-email: Thai Tran <ThaiTran@outlook.com>
Maintainer-email: Thai Tran <ThaiTran@outlook.com>
License: Copyright (c) 2016 The Python Packaging Authority (PyPA)
Project-URL: Homepage, https://github.com/tnmthai/ggee
Project-URL: Bug Reports, https://github.com/tnmthai/ggee/issues
Project-URL: Funding, https://donate.pypi.org
Project-URL: Source, https://github.com/tnmthai/ggee
Keywords: google earth engine,geospatial,data analysis
Classifier: Development Status :: 3 - Alpha
Classifier: Intended Audience :: Developers
Classifier: License :: OSI Approved :: MIT License
Classifier: Programming Language :: Python :: 3
Classifier: Programming Language :: Python :: 3.7
Classifier: Programming Language :: Python :: 3.8
Classifier: Programming Language :: Python :: 3.9
Classifier: Programming Language :: Python :: 3.10
Classifier: Programming Language :: Python :: 3.11
Classifier: Programming Language :: Python :: 3 :: Only
Requires-Python: >=3.7
License-File: LICENSE.txt
